django_admin_edit_mode/__init__.py
django_admin_edit_mode/admin.py
django_admin_edit_mode/list_edit_mode.py
django_admin_edit_mode/templates/admin/change_form_object_tools.html
django_admin_edit_mode/templates/admin/change_list.html
django_admin_edit_mode/templates/admin/edit_mode_button.html
django_admin_edit_mode/templates/admin/readonly_mode_button.html
django_admin_edit_mode/templates/admin/submit_line.html
django_admin_edit_mode-0.1.2.dist-info/LICENSE
django_admin_edit_mode-0.1.2.dist-info/METADATA
django_admin_edit_mode-0.1.2.dist-info/WHEEL
django_admin_edit_mode-0.1.2.dist-info/RECORD
