Metadata-Version: 2.1
Name: django-admin-edit-mode
Version: 0.1.2
Summary: Provides a possibility to open objects in django-admin in read-only mode by default, with a special button "Go to edit mode" to open the same change-object page in regular editable mode.
Home-page: https://github.com/mihasK/django-admin-edit-mode
License: MIT
Author: Your Name
Author-email: you@example.com
Requires-Python: >=3,<4
Classifier: License :: OSI Approved :: MIT License
Classifier: Programming Language :: Python :: 3
Classifier: Programming Language :: Python :: 3.4
Classifier: Programming Language :: Python :: 3.5
Classifier: Programming Language :: Python :: 3.6
Classifier: Programming Language :: Python :: 3.7
Classifier: Programming Language :: Python :: 3.8
Classifier: Programming Language :: Python :: 3.9
Classifier: Programming Language :: Python :: 3.10
Classifier: Programming Language :: Python :: 3.11
Requires-Dist: Django (>=2)
Requires-Dist: django-spurl (==0.6.7)
Project-URL: Repository, https://github.com/mihasK/django-admin-edit-mode
